cyberbullying_detection/__init__.py
cyberbullying_detection/cyberbullying_detection.py
cyberbullying_detection/data/count.pkl
cyberbullying_detection/data/lg.pkl
cyberbullying_detection-2.0.dist-info/LICENSE
cyberbullying_detection-2.0.dist-info/METADATA
cyberbullying_detection-2.0.dist-info/WHEEL
cyberbullying_detection-2.0.dist-info/top_level.txt
cyberbullying_detection-2.0.dist-info/RECORD
