Metadata-Version: 2.1
Name: cyberbullying-detection
Version: 2.0
Summary: An package to detect the cyberbullying content in the text
Home-page: https://github.com/omprakashselvaraj/cyberbullying-0.0.1
Author: Omprakash Selvaraj
Author-email: omprakash.sr2410@gmail.com
Classifier: Programming Language :: Python :: 3.9
Classifier: License :: OSI Approved :: MIT License
Classifier: Operating System :: OS Independent
License-File: LICENSE
Requires-Dist: nltk
Requires-Dist: num2words
Requires-Dist: bs4
Requires-Dist: regex
Requires-Dist: unidecode
